visa_clearing/__init__.py
visa_clearing/cli.py
visa_clearing/exceptions.py
visa_clearing/parser.py
visa_clearing_file_parser-0.0.1.dist-info/METADATA
visa_clearing_file_parser-0.0.1.dist-info/WHEEL
visa_clearing_file_parser-0.0.1.dist-info/entry_points.txt
visa_clearing_file_parser-0.0.1.dist-info/top_level.txt
visa_clearing_file_parser-0.0.1.dist-info/RECORD
