Metadata-Version: 2.4
Name: visa-clearing-file-parser
Version: 0.0.1
Summary: A Python library for parsing Visa BASE II Clearing Transaction Files
Home-page: https://github.com/makafanpeter/visa-clearing-file-parser
Author: Peter Dev
Author-email: Peter Dev <706435+makafanpeter@users.noreply.github.com>
License: MIT
Project-URL: Homepage, https://github.com/makafanpeter/visa-clearing-file-parser
Project-URL: Repository, https://github.com/makafanpeter/visa-clearing-file-parser.git
Project-URL: Bug Tracker, https://github.com/makafanpeter/visa-clearing-file-parser/issues
Keywords: visa,clearing,payment,transaction,finance,baseii
Classifier: Development Status :: 4 - Beta
Classifier: Intended Audience :: Financial and Insurance Industry
Classifier: Topic :: Office/Business :: Financial
Classifier: License :: OSI Approved :: MIT License
Classifier: Programming Language :: Python :: 3
Classifier: Programming Language :: Python :: 3.9
Classifier: Programming Language :: Python :: 3.10
Classifier: Programming Language :: Python :: 3.11
Classifier: Programming Language :: Python :: 3.12
Classifier: Programming Language :: Python :: 3.13
Requires-Python: >=3.8
Provides-Extra: test
Requires-Dist: pytest>=7.0; extra == "test"
Requires-Dist: pytest-cov>=4.0; extra == "test"
Requires-Dist: coverage>=7.0; extra == "test"
Requires-Dist: flake8>=6.0; extra == "test"
Provides-Extra: dev
Requires-Dist: pytest>=7.0; extra == "dev"
Requires-Dist: pytest-cov>=4.0; extra == "dev"
Requires-Dist: coverage>=7.0; extra == "dev"
Requires-Dist: black>=23.0; extra == "dev"
Requires-Dist: flake8>=6.0; extra == "dev"
Requires-Dist: mypy>=1.0; extra == "dev"
Requires-Dist: build>=0.10.0; extra == "dev"
Requires-Dist: twine>=4.0.0; extra == "dev"
Dynamic: author
Dynamic: home-page
Dynamic: requires-python
